<?xml version="1.0" ?>
<annotation>
	<folder>visdrone</folder>
	<filename>13000122</filename>
	<source>
		<database>Unknown</database>
	</source>
	<size>
		<width>640</width>
		<height>640</height>
		<depth>3</depth>
	</size>
	<segmented>0</segmented>
	<object>
		<name>open</name>
		<pose>Unspecified</pose>
		<truncated>1</truncated>
		<difficult>0</difficult>
		<bndbox>
			<xmin>179</xmin>
			<ymin>337</ymin>
			<xmax>215</xmax>
			<ymax>368</ymax>
		</bndbox>
	</object>
	<object>
		<name>mousebite</name>
		<pose>Unspecified</pose>
		<truncated>1</truncated>
		<difficult>0</difficult>
		<bndbox>
			<xmin>89</xmin>
			<ymin>255</ymin>
			<xmax>118</xmax>
			<ymax>288</ymax>
		</bndbox>
	</object>
	<object>
		<name>spur</name>
		<pose>Unspecified</pose>
		<truncated>1</truncated>
		<difficult>0</difficult>
		<bndbox>
			<xmin>188</xmin>
			<ymin>159</ymin>
			<xmax>223</xmax>
			<ymax>188</ymax>
		</bndbox>
	</object>
	<object>
		<name>copper</name>
		<pose>Unspecified</pose>
		<truncated>1</truncated>
		<difficult>0</difficult>
		<bndbox>
			<xmin>439</xmin>
			<ymin>460</ymin>
			<xmax>473</xmax>
			<ymax>491</ymax>
		</bndbox>
	</object>
	<object>
		<name>pin-hole</name>
		<pose>Unspecified</pose>
		<truncated>1</truncated>
		<difficult>0</difficult>
		<bndbox>
			<xmin>440</xmin>
			<ymin>285</ymin>
			<xmax>476</xmax>
			<ymax>325</ymax>
		</bndbox>
	</object>
</annotation>
