<?xml version="1.0" ?>
<annotation>
	<folder>visdrone</folder>
	<filename>13000038</filename>
	<source>
		<database>Unknown</database>
	</source>
	<size>
		<width>640</width>
		<height>640</height>
		<depth>3</depth>
	</size>
	<segmented>0</segmented>
	<object>
		<name>open</name>
		<pose>Unspecified</pose>
		<truncated>1</truncated>
		<difficult>0</difficult>
		<bndbox>
			<xmin>335</xmin>
			<ymin>251</ymin>
			<xmax>372</xmax>
			<ymax>279</ymax>
		</bndbox>
	</object>
	<object>
		<name>short</name>
		<pose>Unspecified</pose>
		<truncated>1</truncated>
		<difficult>0</difficult>
		<bndbox>
			<xmin>188</xmin>
			<ymin>195</ymin>
			<xmax>361</xmax>
			<ymax>229</ymax>
		</bndbox>
	</object>
	<object>
		<name>mousebite</name>
		<pose>Unspecified</pose>
		<truncated>1</truncated>
		<difficult>0</difficult>
		<bndbox>
			<xmin>182</xmin>
			<ymin>305</ymin>
			<xmax>215</xmax>
			<ymax>336</ymax>
		</bndbox>
	</object>
	<object>
		<name>spur</name>
		<pose>Unspecified</pose>
		<truncated>1</truncated>
		<difficult>0</difficult>
		<bndbox>
			<xmin>187</xmin>
			<ymin>258</ymin>
			<xmax>231</xmax>
			<ymax>287</ymax>
		</bndbox>
	</object>
	<object>
		<name>copper</name>
		<pose>Unspecified</pose>
		<truncated>1</truncated>
		<difficult>0</difficult>
		<bndbox>
			<xmin>456</xmin>
			<ymin>307</ymin>
			<xmax>493</xmax>
			<ymax>347</ymax>
		</bndbox>
	</object>
	<object>
		<name>pin-hole</name>
		<pose>Unspecified</pose>
		<truncated>1</truncated>
		<difficult>0</difficult>
		<bndbox>
			<xmin>161</xmin>
			<ymin>410</ymin>
			<xmax>191</xmax>
			<ymax>444</ymax>
		</bndbox>
	</object>
	<object>
		<name>mousebite</name>
		<pose>Unspecified</pose>
		<truncated>1</truncated>
		<difficult>0</difficult>
		<bndbox>
			<xmin>52</xmin>
			<ymin>447</ymin>
			<xmax>88</xmax>
			<ymax>474</ymax>
		</bndbox>
	</object>
</annotation>
