<?xml version="1.0" ?>
<annotation>
	<folder>visdrone</folder>
	<filename>20085182</filename>
	<source>
		<database>Unknown</database>
	</source>
	<size>
		<width>640</width>
		<height>640</height>
		<depth>3</depth>
	</size>
	<segmented>0</segmented>
	<object>
		<name>short</name>
		<pose>Unspecified</pose>
		<truncated>1</truncated>
		<difficult>0</difficult>
		<bndbox>
			<xmin>200</xmin>
			<ymin>483</ymin>
			<xmax>305</xmax>
			<ymax>539</ymax>
		</bndbox>
	</object>
	<object>
		<name>mousebite</name>
		<pose>Unspecified</pose>
		<truncated>1</truncated>
		<difficult>0</difficult>
		<bndbox>
			<xmin>354</xmin>
			<ymin>399</ymin>
			<xmax>385</xmax>
			<ymax>428</ymax>
		</bndbox>
	</object>
	<object>
		<name>mousebite</name>
		<pose>Unspecified</pose>
		<truncated>1</truncated>
		<difficult>0</difficult>
		<bndbox>
			<xmin>187</xmin>
			<ymin>395</ymin>
			<xmax>214</xmax>
			<ymax>421</ymax>
		</bndbox>
	</object>
	<object>
		<name>mousebite</name>
		<pose>Unspecified</pose>
		<truncated>1</truncated>
		<difficult>0</difficult>
		<bndbox>
			<xmin>307</xmin>
			<ymin>402</ymin>
			<xmax>337</xmax>
			<ymax>431</ymax>
		</bndbox>
	</object>
	<object>
		<name>copper</name>
		<pose>Unspecified</pose>
		<truncated>1</truncated>
		<difficult>0</difficult>
		<bndbox>
			<xmin>425</xmin>
			<ymin>509</ymin>
			<xmax>457</xmax>
			<ymax>538</ymax>
		</bndbox>
	</object>
</annotation>
