<?xml version="1.0" ?>
<annotation>
	<folder>visdrone</folder>
	<filename>44000013</filename>
	<source>
		<database>Unknown</database>
	</source>
	<size>
		<width>640</width>
		<height>640</height>
		<depth>3</depth>
	</size>
	<segmented>0</segmented>
	<object>
		<name>open</name>
		<pose>Unspecified</pose>
		<truncated>1</truncated>
		<difficult>0</difficult>
		<bndbox>
			<xmin>327</xmin>
			<ymin>106</ymin>
			<xmax>367</xmax>
			<ymax>148</ymax>
		</bndbox>
	</object>
	<object>
		<name>open</name>
		<pose>Unspecified</pose>
		<truncated>1</truncated>
		<difficult>0</difficult>
		<bndbox>
			<xmin>466</xmin>
			<ymin>161</ymin>
			<xmax>499</xmax>
			<ymax>194</ymax>
		</bndbox>
	</object>
	<object>
		<name>short</name>
		<pose>Unspecified</pose>
		<truncated>1</truncated>
		<difficult>0</difficult>
		<bndbox>
			<xmin>436</xmin>
			<ymin>85</ymin>
			<xmax>458</xmax>
			<ymax>140</ymax>
		</bndbox>
	</object>
	<object>
		<name>short</name>
		<pose>Unspecified</pose>
		<truncated>1</truncated>
		<difficult>0</difficult>
		<bndbox>
			<xmin>306</xmin>
			<ymin>197</ymin>
			<xmax>331</xmax>
			<ymax>247</ymax>
		</bndbox>
	</object>
	<object>
		<name>mousebite</name>
		<pose>Unspecified</pose>
		<truncated>1</truncated>
		<difficult>0</difficult>
		<bndbox>
			<xmin>347</xmin>
			<ymin>59</ymin>
			<xmax>373</xmax>
			<ymax>94</ymax>
		</bndbox>
	</object>
	<object>
		<name>mousebite</name>
		<pose>Unspecified</pose>
		<truncated>1</truncated>
		<difficult>0</difficult>
		<bndbox>
			<xmin>538</xmin>
			<ymin>95</ymin>
			<xmax>568</xmax>
			<ymax>127</ymax>
		</bndbox>
	</object>
	<object>
		<name>spur</name>
		<pose>Unspecified</pose>
		<truncated>1</truncated>
		<difficult>0</difficult>
		<bndbox>
			<xmin>466</xmin>
			<ymin>74</ymin>
			<xmax>496</xmax>
			<ymax>108</ymax>
		</bndbox>
	</object>
	<object>
		<name>spur</name>
		<pose>Unspecified</pose>
		<truncated>1</truncated>
		<difficult>0</difficult>
		<bndbox>
			<xmin>589</xmin>
			<ymin>208</ymin>
			<xmax>625</xmax>
			<ymax>237</ymax>
		</bndbox>
	</object>
	<object>
		<name>copper</name>
		<pose>Unspecified</pose>
		<truncated>1</truncated>
		<difficult>0</difficult>
		<bndbox>
			<xmin>203</xmin>
			<ymin>423</ymin>
			<xmax>237</xmax>
			<ymax>461</ymax>
		</bndbox>
	</object>
	<object>
		<name>pin-hole</name>
		<pose>Unspecified</pose>
		<truncated>1</truncated>
		<difficult>0</difficult>
		<bndbox>
			<xmin>225</xmin>
			<ymin>188</ymin>
			<xmax>247</xmax>
			<ymax>227</ymax>
		</bndbox>
	</object>
</annotation>
