<?xml version="1.0" ?>
<annotation>
	<folder>visdrone</folder>
	<filename>92000021</filename>
	<source>
		<database>Unknown</database>
	</source>
	<size>
		<width>640</width>
		<height>640</height>
		<depth>3</depth>
	</size>
	<segmented>0</segmented>
	<object>
		<name>open</name>
		<pose>Unspecified</pose>
		<truncated>1</truncated>
		<difficult>0</difficult>
		<bndbox>
			<xmin>202</xmin>
			<ymin>368</ymin>
			<xmax>284</xmax>
			<ymax>409</ymax>
		</bndbox>
	</object>
	<object>
		<name>spur</name>
		<pose>Unspecified</pose>
		<truncated>1</truncated>
		<difficult>0</difficult>
		<bndbox>
			<xmin>346</xmin>
			<ymin>268</ymin>
			<xmax>383</xmax>
			<ymax>302</ymax>
		</bndbox>
	</object>
	<object>
		<name>pin-hole</name>
		<pose>Unspecified</pose>
		<truncated>1</truncated>
		<difficult>0</difficult>
		<bndbox>
			<xmin>469</xmin>
			<ymin>363</ymin>
			<xmax>494</xmax>
			<ymax>396</ymax>
		</bndbox>
	</object>
	<object>
		<name>mousebite</name>
		<pose>Unspecified</pose>
		<truncated>1</truncated>
		<difficult>0</difficult>
		<bndbox>
			<xmin>102</xmin>
			<ymin>270</ymin>
			<xmax>167</xmax>
			<ymax>308</ymax>
		</bndbox>
	</object>
	<object>
		<name>copper</name>
		<pose>Unspecified</pose>
		<truncated>1</truncated>
		<difficult>0</difficult>
		<bndbox>
			<xmin>112</xmin>
			<ymin>37</ymin>
			<xmax>146</xmax>
			<ymax>73</ymax>
		</bndbox>
	</object>
</annotation>
