<?xml version="1.0" ?>
<annotation>
	<folder>visdrone</folder>
	<filename>92000100</filename>
	<source>
		<database>Unknown</database>
	</source>
	<size>
		<width>640</width>
		<height>640</height>
		<depth>3</depth>
	</size>
	<segmented>0</segmented>
	<object>
		<name>open</name>
		<pose>Unspecified</pose>
		<truncated>1</truncated>
		<difficult>0</difficult>
		<bndbox>
			<xmin>70</xmin>
			<ymin>339</ymin>
			<xmax>151</xmax>
			<ymax>382</ymax>
		</bndbox>
	</object>
	<object>
		<name>short</name>
		<pose>Unspecified</pose>
		<truncated>1</truncated>
		<difficult>0</difficult>
		<bndbox>
			<xmin>219</xmin>
			<ymin>328</ymin>
			<xmax>309</xmax>
			<ymax>363</ymax>
		</bndbox>
	</object>
	<object>
		<name>spur</name>
		<pose>Unspecified</pose>
		<truncated>1</truncated>
		<difficult>0</difficult>
		<bndbox>
			<xmin>168</xmin>
			<ymin>240</ymin>
			<xmax>203</xmax>
			<ymax>286</ymax>
		</bndbox>
	</object>
	<object>
		<name>copper</name>
		<pose>Unspecified</pose>
		<truncated>1</truncated>
		<difficult>0</difficult>
		<bndbox>
			<xmin>271</xmin>
			<ymin>185</ymin>
			<xmax>311</xmax>
			<ymax>228</ymax>
		</bndbox>
	</object>
	<object>
		<name>pin-hole</name>
		<pose>Unspecified</pose>
		<truncated>1</truncated>
		<difficult>0</difficult>
		<bndbox>
			<xmin>390</xmin>
			<ymin>276</ymin>
			<xmax>430</xmax>
			<ymax>317</ymax>
		</bndbox>
	</object>
</annotation>
